contact_locations_local/__init__.py
contact_locations_local/contact_locations_local.py
contact_locations_local/contact_locations_local_constants.py
contact_locations_local-0.0.9.dist-info/METADATA
contact_locations_local-0.0.9.dist-info/WHEEL
contact_locations_local-0.0.9.dist-info/top_level.txt
contact_locations_local-0.0.9.dist-info/RECORD
