Metadata-Version: 2.1
Name: contact-locations-local
Version: 0.0.9
Summary: PyPI Package for Circles contact-locations-local Python
Home-page: https://github.com/circles-zone/contact-location-local-python-package
Author: Circles
Author-email: info@circlez.ai
Classifier: Programming Language :: Python :: 3
Classifier: License :: Other/Proprietary License
Classifier: Operating System :: OS Independent
Requires-Dist: PyMySQL >=1.0.2
Requires-Dist: pytest >=7.4.0
Requires-Dist: mysql-connector >=2.2.9
Requires-Dist: logzio-python-handler >=4.1.0
Requires-Dist: user-context-remote >=0.0.57
Requires-Dist: python-sdk-remote >=0.0.27
Requires-Dist: location-local >=0.0.83
Requires-Dist: language-remote >=0.0.10
